[{"id":"58239d73.30c134","type":"file in","z":"35ddaf8.f276a5","name":"","filename":"/tmp/node-red.png","format":"","chunk":false,"sendError":false,"encoding":"none","x":290,"y":300,"wires":[["f3ea19ee.f08518"]]},{"id":"54ef025d.56fccc","type":"template","z":"35ddaf8.f276a5","name":"","field":"payload","fieldType":"msg","format":"json","syntax":"mustache","template":"{\n    \"pageSize\": \"A4\",\n    \"pageOrientation\": \"portrait\",\n    \"pageMargins\": [\n        40,\n        60,\n        40,\n        60\n    ],\n    \"info\": {\n        \"title\": \"awesome Document\",\n        \"author\": \"john doe\",\n        \"subject\": \"subject of document\",\n        \"keywords\": \"keywords for document\"\n    },\n    \"content\": [\n        \"etiquette UPS\",\n        {\n            \"image\": \"data:image/png;base64,{{{payload}}}\",\n            \"width\": 200\n        },\n        \"Sample SVG\",\n        {\n            \"svg\": \"<svg width=\\\"300\\\" height=\\\"200\\\" viewBox=\\\"0 0 300 200\\\"><polygon points=\\\"100,10 40,198 190,78 10,78 160,198\\\" style=\\\"fill:lime;stroke:purple;stroke-width:5;fill-rule:evenodd;stroke-linecap:round;\\\"/></svg>\",\n            \"width\": 150\n        }\n\n    ]\n}","output":"json","x":600,"y":300,"wires":[["bdd7feab.d9412"]]},{"id":"57c0a23a.ab3bec","type":"file","z":"35ddaf8.f276a5","name":"","filename":"test.pdf","appendNewline":false,"createDir":false,"overwriteFile":"true","encoding":"none","x":900,"y":340,"wires":[[]]},{"id":"bdd7feab.d9412","type":"pdfmake","z":"35ddaf8.f276a5","name":"","outputType":"Buffer","inputProperty":"payload","options":"{}","outputProperty":"payload","x":740,"y":300,"wires":[["18891720.d5c069"]]},{"id":"f3ea19ee.f08518","type":"base64","z":"35ddaf8.f276a5","name":"","action":"str","property":"payload","x":460,"y":300,"wires":[["54ef025d.56fccc"]]},{"id":"69f3ab2a.706414","type":"http in","z":"35ddaf8.f276a5","name":"","url":"/pdf","method":"get","upload":false,"swaggerDoc":"","x":120,"y":300,"wires":[["58239d73.30c134"]]},{"id":"18891720.d5c069","type":"change","z":"35ddaf8.f276a5","name":"Set Headers","rules":[{"t":"set","p":"headers","pt":"msg","to":"{}","tot":"json"},{"t":"set","p":"headers.content-type","pt":"msg","to":"application/pdf","tot":"str"}],"action":"","property":"","from":"","to":"","reg":false,"x":910,"y":300,"wires":[["bb8968bb.603638"]]},{"id":"bb8968bb.603638","type":"http response","z":"35ddaf8.f276a5","name":"","x":1050,"y":300,"wires":[]},{"id":"bdc1cefd.53b66","type":"comment","z":"35ddaf8.f276a5","name":"cree dynamiquement un fichier PDF","info":"","x":200,"y":240,"wires":[]}]